pykhoj/__init__.py
pykhoj/main.py
pykhoj-1.0.dev2.dist-info/DESCRIPTION.rst
pykhoj-1.0.dev2.dist-info/METADATA
pykhoj-1.0.dev2.dist-info/RECORD
pykhoj-1.0.dev2.dist-info/WHEEL
pykhoj-1.0.dev2.dist-info/metadata.json
pykhoj-1.0.dev2.dist-info/top_level.txt
