Metadata-Version: 2.0
Name: pykhoj
Version: 1.0.dev2
Summary: Python package for exploratory data analysis
Home-page: https://github.com/sagarkar10/pykhoj
Author: Sagar Kar
Author-email: sagarkar10@gmail.com
License: UNKNOWN
Platform: UNKNOWN
Classifier: Development Status :: 3 - Alpha
Classifier: Intended Audience :: Developers
Classifier: Topic :: Software Development :: Build Tools
Classifier: License :: OSI Approved :: MIT License
Classifier: Programming Language :: Python :: 3
Requires-Dist: numpy
Requires-Dist: pandas
Requires-Dist: matplotlib
Requires-Dist: seaborn
